esahub/__init__.py
esahub/check.py
esahub/checksum.py
esahub/cli.py
esahub/config.py
esahub/config.yaml
esahub/geo.py
esahub/main.py
esahub/scihub.py
esahub/tty.py
esahub/utils.py
esahub/tests/__init__.py
esahub/tests/config.py
esahub/tests/test_all.py
esahub-0.1.6.dist-info/METADATA
esahub-0.1.6.dist-info/RECORD
esahub-0.1.6.dist-info/WHEEL
esahub-0.1.6.dist-info/entry_points.txt
esahub-0.1.6.dist-info/top_level.txt
