Metadata-Version: 2.1
Name: esahub
Version: 0.1.6
Summary: A Python module for downloading ESA satellite data
Home-page: https://github.com/jnhansen/esahub
Author: Johannes Hansen
Author-email: johannes.hansen@ed.ac.uk
License: MIT
Keywords: esahub,scihub,sentinel,satellite,copernicus
Platform: UNKNOWN
Classifier: Intended Audience :: Science/Research
Classifier: Intended Audience :: Developers
Classifier: Natural Language :: English
Classifier: Programming Language :: Python
Classifier: Programming Language :: Python :: 3.5
Classifier: Programming Language :: Python :: 3.6
Classifier: Programming Language :: Python :: 3.7
Requires-Dist: pyyaml
Requires-Dist: numpy
Requires-Dist: lxml
Requires-Dist: shapely
Requires-Dist: python-dateutil
Requires-Dist: pytz
Requires-Dist: tqdm
Requires-Dist: aiohttp
